Workbook

Sheet APMMDB
A1: Task | B1: MU | C1: Node | D1: Session | E1: Uproc | F1: Start Date | G1: End Date | H1: Task-lookup_UAC | I1: Average Running Duration | J1: NOTE
A2: CASE_PACK_EXPORT | B2: PMMDB | C2: apmmdb | D2: CSP_EXPORT | E2: H_CSP_EXPORT | F2: 21/12/2025 19:59:05 | G2: 21/12/2025 19:59:07 | H2: =VLOOKUP(E2,UAC!A:A,1,FALSE) -> #N/A | I2: 31s
A3: CASE_PACK_EXPORT | B3: PMMDB | C3: apmmdb | D3: CSP_EXPORT | E3: H_CSP_EXPORT | F3: 22/12/2025 20:16:07 | G3: 22/12/2025 20:16:09 | H3: =VLOOKUP(E3,UAC!A:A,1,FALSE) -> #N/A
A4: CASE_PACK_EXPORT | B4: PMMDB | C4: apmmdb | D4: CSP_EXPORT | E4: JDA_PMM_CSP_EXPORT_CASEPACK | F4: 21/12/2025 19:59:08 | G4: 21/12/2025 19:59:16 | H4: =VLOOKUP(E4,UAC!A:A,1,FALSE) -> JDA_PMM_CSP_EXPORT_CASEPACK | I4: 6s
A5: CASE_PACK_EXPORT | B5: PMMDB | C5: apmmdb | D5: CSP_EXPORT | E5: JDA_PMM_CSP_EXPORT_CASEPACK | F5: 22/12/2025 20:16:09 | G5: 22/12/2025 20:16:19 | H5: =VLOOKUP(E5,UAC!A:A,1,FALSE) -> JDA_PMM_CSP_EXPORT_CASEPACK
A6: CASE_PACK_EXPORT | B6: PMMDB | C6: apmmdb | D6: CSP_EXPORT | E6: JDA_PMM_CSP_EXPORT_CASEPACK_AF | F6: 21/12/2025 19:59:08 | G6: 21/12/2025 19:59:37 | H6: =VLOOKUP(E6,UAC!A:A,1,FALSE) -> JDA_PMM_CSP_EXPORT_CASEPACK_AF | I6: 1s
A7: CASE_PACK_EXPORT | B7: PMMDB | C7: apmmdb | D7: CSP_EXPORT | E7: JDA_PMM_CSP_EXPORT_CASEPACK_AF | F7: 22/12/2025 20:16:09 | G7: 22/12/2025 20:16:37 | H7: =VLOOKUP(E7,UAC!A:A,1,FALSE) -> JDA_PMM_CSP_EXPORT_CASEPACK_AF
A8: CASE_PACK_EXPORT | B8: PMMDB | C8: apmmdb | D8: CSP_EXPORT | E8: JDA_PMM_CSP_EXPORT_CASEPACK_COST | F8: 21/12/2025 19:59:08 | G8: 21/12/2025 19:59:22 | H8: =VLOOKUP(E8,UAC!A:A,1,FALSE) -> JDA_PMM_CSP_EXPORT_CASEPACK_COST | I8: 13s
A9: CASE_PACK_EXPORT | B9: PMMDB | C9: apmmdb | D9: CSP_EXPORT | E9: JDA_PMM_CSP_EXPORT_CASEPACK_COST | F9: 22/12/2025 20:16:09 | G9: 22/12/2025 20:16:26 | H9: =VLOOKUP(E9,UAC!A:A,1,FALSE) -> JDA_PMM_CSP_EXPORT_CASEPACK_COST
A10: CASE_PACK_EXPORT | B10: PMMDB | C10: apmmdb | D10: CSP_EXPORT | E10: JDA_PMM_CSP_EXPORT_CASEPACK_FLAT | F10: 21/12/2025 19:59:38 | G10: 21/12/2025 19:59:56 | H10: =VLOOKUP(E10,UAC!A:A,1,FALSE) -> JDA_PMM_CSP_EXPORT_CASEPACK_FLAT | I10: 6s
A11: CASE_PACK_EXPORT | B11: PMMDB | C11: apmmdb | D11: CSP_EXPORT | E11: JDA_PMM_CSP_EXPORT_CASEPACK_FLAT | F11: 22/12/2025 20:16:37 | G11: 22/12/2025 20:17:04 | H11: =VLOOKUP(E11,UAC!A:A,1,FALSE) -> JDA_PMM_CSP_EXPORT_CASEPACK_FLAT
A12: CASE_PACK_EXPORT | B12: PMMDB | C12: apmmdb | D12: CSP_EXPORT | E12: JDA_PMM_CSP_REJECT_REP | F12: 21/12/2025 19:59:57 | G12: 21/12/2025 20:00:05 | H12: =VLOOKUP(E12,UAC!A:A,1,FALSE) -> JDA_PMM_CSP_REJECT_REP | I12: 1s
A13: CASE_PACK_EXPORT | B13: PMMDB | C13: apmmdb | D13: CSP_EXPORT | E13: JDA_PMM_CSP_REJECT_REP | F13: 22/12/2025 20:17:04 | G13: 22/12/2025 20:17:10 | H13: =VLOOKUP(E13,UAC!A:A,1,FALSE) -> JDA_PMM_CSP_REJECT_REP
A14: CASE_PACK_EXPORT | B14: PMMDB | C14: apmmdb | D14: CSP_EXPORT | E14: JDA_PMM_EXPORT_CHG_ALLOW | F14: 21/12/2025 19:59:08 | G14: 21/12/2025 19:59:16 | H14: =VLOOKUP(E14,UAC!A:A,1,FALSE) -> JDA_PMM_EXPORT_CHG_ALLOW | I14: 1s
A15: CASE_PACK_EXPORT | B15: PMMDB | C15: apmmdb | D15: CSP_EXPORT | E15: JDA_PMM_EXPORT_CHG_ALLOW | F15: 22/12/2025 20:16:09 | G15: 22/12/2025 20:16:17 | H15: =VLOOKUP(E15,UAC!A:A,1,FALSE) -> JDA_PMM_EXPORT_CHG_ALLOW
A16: CASE_PACK_EXPORT | B16: PMMDB | C16: apmmdb | D16: CSP_EXPORT | E16: T_CSP_EXPORT | F16: 21/12/2025 20:00:05 | G16: 21/12/2025 20:00:11 | H16: =VLOOKUP(E16,UAC!A:A,1,FALSE) -> #N/A | I16: 6s
A17: CASE_PACK_EXPORT | B17: PMMDB | C17: apmmdb | D17: CSP_EXPORT | E17: T_CSP_EXPORT | F17: 22/12/2025 20:17:10 | G17: 22/12/2025 20:17:16 | H17: =VLOOKUP(E17,UAC!A:A,1,FALSE) -> #N/A
A18: IMPORT_PRM_TO_PMM | B18: PMMDB | C18: apmmdb | D18: IMP_PRM_PMM | E18: H_IMP_PRM_TO_PROMO | F18: 21/12/2025 22:24:05 | G18: 21/12/2025 22:24:07 | H18: =VLOOKUP(E18,UAC!A:A,1,FALSE) -> #N/A | I18: 1s
A19: IMPORT_PRM_TO_PMM | B19: PMMDB | C19: apmmdb | D19: IMP_PRM_PMM | E19: H_IMP_PRM_TO_PROMO | F19: 22/12/2025 22:20:15 | G19: 22/12/2025 22:20:18 | H19: =VLOOKUP(E19,UAC!A:A,1,FALSE) -> #N/A
A20: IMPORT_PRM_TO_PMM | B20: PMMDB | C20: apmmdb | D20: IMP_PRM_PMM | E20: JDA_PMM_IMPORT_PO_ALLOCATION | F20: 21/12/2025 22:24:10 | G20: 21/12/2025 22:24:11 | H20: =VLOOKUP(E20,UAC!A:A,1,FALSE) -> JDA_PMM_IMPORT_PO_ALLOCATION | I20: 6s
A21: IMPORT_PRM_TO_PMM | B21: PMMDB | C21: apmmdb | D21: IMP_PRM_PMM | E21: JDA_PMM_IMPORT_PO_ALLOCATION | F21: 22/12/2025 22:20:20 | G21: 22/12/2025 22:20:21 | H21: =VLOOKUP(E21,UAC!A:A,1,FALSE) -> JDA_PMM_IMPORT_PO_ALLOCATION
A22: IMPORT_PRM_TO_PMM | B22: PMMDB | C22: apmmdb | D22: IMP_PRM_PMM | E22: JDA_PMM_IMPORT_PROMO | F22: 21/12/2025 22:24:08 | G22: 21/12/2025 22:24:09 | H22: =VLOOKUP(E22,UAC!A:A,1,FALSE) -> JDA_PMM_IMPORT_PROMO | I22: 31s
A23: IMPORT_PRM_TO_PMM | B23: PMMDB | C23: apmmdb | D23: IMP_PRM_PMM | E23: JDA_PMM_IMPORT_PROMO | F23: 22/12/2025 22:20:18 | G23: 22/12/2025 22:20:19 | H23: =VLOOKUP(E23,UAC!A:A,1,FALSE) -> JDA_PMM_IMPORT_PROMO
A24: IMPORT_PRM_TO_PMM | B24: PMMDB | C24: apmmdb | D24: IMP_PRM_PMM | E24: T_IMP_PRM_TO_PROMO | F24: 21/12/2025 22:24:12 | G24: 21/12/2025 22:24:14 | H24: =VLOOKUP(E24,UAC!A:A,1,FALSE) -> #N/A | I24: 1s
A25: IMPORT_PRM_TO_PMM | B25: PMMDB | C25: apmmdb | D25: IMP_PRM_PMM | E25: T_IMP_PRM_TO_PROMO | F25: 22/12/2025 22:20:21 | G25: 22/12/2025 22:20:23 | H25: =VLOOKUP(E25,UAC!A:A,1,FALSE) -> #N/A
A26: IMPORT_PROCS | B26: PMMDB | C26: apmmdb | D26: IMPORT_PROCS | E26: H_IMP_PROC | F26: 21/12/2025 19:00:58 | G26: 21/12/2025 19:01:00 | H26: =VLOOKUP(E26,UAC!A:A,1,FALSE) -> #N/A | I26: 6s
A27: IMPORT_PROCS | B27: PMMDB | C27: apmmdb | D27: IMPORT_PROCS | E27: H_IMP_PROC | F27: 22/12/2025 19:16:57 | G27: 22/12/2025 19:16:59 | H27: =VLOOKUP(E27,UAC!A:A,1,FALSE) -> #N/A
A28: IMPORT_PROCS | B28: PMMDB | C28: apmmdb | D28: IMPORT_PROCS | E28: JDA_PMM_IMPORT_PLANOGRAM | F28: 21/12/2025 19:01:10 | G28: 21/12/2025 19:25:24 | H28: =VLOOKUP(E28,UAC!A:A,1,FALSE) -> JDA_PMM_IMPORT_PLANOGRAM | I28: 31s
A29: IMPORT_PROCS | B29: PMMDB | C29: apmmdb | D29: IMPORT_PROCS | E29: JDA_PMM_IMPORT_PLANOGRAM | F29: 22/12/2025 19:17:17 | G29: 22/12/2025 19:37:11 | H29: =VLOOKUP(E29,UAC!A:A,1,FALSE) -> JDA_PMM_IMPORT_PLANOGRAM
A30: IMPORT_PROCS | B30: PMMDB | C30: apmmdb | D30: IMPORT_PROCS | E30: JDA_PMM_INT_NOTIFICATIONS | F30: 21/12/2025 19:01:00 | G30: 21/12/2025 19:01:10 | H30: =VLOOKUP(E30,UAC!A:A,1,FALSE) -> JDA_PMM_INT_NOTIFICATIONS | I30: 1s
A31: IMPORT_PROCS | B31: PMMDB | C31: apmmdb | D31: IMPORT_PROCS | E31: JDA_PMM_INT_NOTIFICATIONS | F31: 22/12/2025 19:17:00 | G31: 22/12/2025 19:17:17 | H31: =VLOOKUP(E31,UAC!A:A,1,FALSE) -> JDA_PMM_INT_NOTIFICATIONS
A32: IMPORT_PROCS | B32: PMMDB | C32: apmmdb | D32: IMPORT_PROCS | E32: T_IMP_PROC | F32: 21/12/2025 19:25:24 | G32: 21/12/2025 19:25:30 | H32: =VLOOKUP(E32,UAC!A:A,1,FALSE) -> #N/A | I32: 13s
A33: IMPORT_PROCS | B33: PMMDB | C33: apmmdb | D33: IMPORT_PROCS | E33: T_IMP_PROC | F33: 22/12/2025 19:37:11 | G33: 22/12/2025 19:37:17 | H33: =VLOOKUP(E33,UAC!A:A,1,FALSE) -> #N/A
A34: ITEM_EXPORT | B34: PMMDB | C34: apmmdb | D34: ITM_EXPORT | E34: H_ITM_EXPORT | F34: 21/12/2025 19:30:28 | G34: 21/12/2025 19:30:30 | H34: =VLOOKUP(E34,UAC!A:A,1,FALSE) -> #N/A | I34: 31s
A35: ITEM_EXPORT | B35: PMMDB | C35: apmmdb | D35: ITM_EXPORT | E35: H_ITM_EXPORT | F35: 22/12/2025 19:43:03 | G35: 22/12/2025 19:43:06 | H35: =VLOOKUP(E35,UAC!A:A,1,FALSE) -> #N/A
A36: ITEM_EXPORT | B36: PMMDB | C36: apmmdb | D36: ITM_EXPORT | E36: JDA_PMM_ITM_ATTR_MAINT | F36: 21/12/2025 19:41:06 | G36: 21/12/2025 19:58:17 | H36: =VLOOKUP(E36,UAC!A:A,1,FALSE) -> JDA_PMM_ITM_ATTR_MAINT | I36: 6s
A37: ITEM_EXPORT | B37: PMMDB | C37: apmmdb | D37: ITM_EXPORT | E37: JDA_PMM_ITM_ATTR_MAINT | F37: 22/12/2025 19:59:33 | G37: 22/12/2025 20:15:24 | H37: =VLOOKUP(E37,UAC!A:A,1,FALSE) -> JDA_PMM_ITM_ATTR_MAINT
A38: ITEM_EXPORT | B38: PMMDB | C38: apmmdb | D38: ITM_EXPORT | E38: JDA_PMM_ITM_EXPORT_ITEM_AF | F38: 21/12/2025 19:30:30 | G38: 21/12/2025 19:30:57 | H38: =VLOOKUP(E38,UAC!A:A,1,FALSE) -> JDA_PMM_ITM_EXPORT_ITEM_AF | I38: 6s
A39: ITEM_EXPORT | B39: PMMDB | C39: apmmdb | D39: ITM_EXPORT | E39: JDA_PMM_ITM_EXPORT_ITEM_AF | F39: 22/12/2025 19:43:06 | G39: 22/12/2025 19:43:50 | H39: =VLOOKUP(E39,UAC!A:A,1,FALSE) -> JDA_PMM_ITM_EXPORT_ITEM_AF
A40: ITEM_EXPORT | B40: PMMDB | C40: apmmdb | D40: ITM_EXPORT | E40: JDA_PMM_ITM_EXPORT_ITEM_ATTRIBUTE | F40: 21/12/2025 19:30:30 | G40: 21/12/2025 19:31:54 | H40: =VLOOKUP(E40,UAC!A:A,1,FALSE) -> JDA_PMM_ITM_EXPORT_ITEM_ATTRIBUTE | I40: 6s
A41: ITEM_EXPORT | B41: PMMDB | C41: apmmdb | D41: ITM_EXPORT | E41: JDA_PMM_ITM_EXPORT_ITEM_ATTRIBUTE | F41: 22/12/2025 19:43:07 | G41: 22/12/2025 19:45:26 | H41: =VLOOKUP(E41,UAC!A:A,1,FALSE) -> JDA_PMM_ITM_EXPORT_ITEM_ATTRIBUTE
A42: ITEM_EXPORT | B42: PMMDB | C42: apmmdb | D42: ITM_EXPORT | E42: JDA_PMM_ITM_EXPORT_ITEM_HIER | F42: 21/12/2025 19:30:31 | G42: 21/12/2025 19:30:46 | H42: =VLOOKUP(E42,UAC!A:A,1,FALSE) -> JDA_PMM_ITM_EXPORT_ITEM_HIER | I42: 1s
A43: ITEM_EXPORT | B43: PMMDB | C43: apmmdb | D43: ITM_EXPORT | E43: JDA_PMM_ITM_EXPORT_ITEM_HIER | F43: 22/12/2025 19:43:06 | G43: 22/12/2025 19:43:26 | H43: =VLOOKUP(E43,UAC!A:A,1,FALSE) -> JDA_PMM_ITM_EXPORT_ITEM_HIER
A44: ITEM_EXPORT | B44: PMMDB | C44: apmmdb | D44: ITM_EXPORT | E44: JDA_PMM_ITM_EXPORT_ITEM_MASTER | F44: 21/12/2025 19:30:31 | G44: 21/12/2025 19:30:46 | H44: =VLOOKUP(E44,UAC!A:A,1,FALSE) -> JDA_PMM_ITM_EXPORT_ITEM_MASTER | I44: 1s
A45: ITEM_EXPORT | B45: PMMDB | C45: apmmdb | D45: ITM_EXPORT | E45: JDA_PMM_ITM_EXPORT_ITEM_MASTER | F45: 22/12/2025 19:43:07 | G45: 22/12/2025 19:43:20 | H45: =VLOOKUP(E45,UAC!A:A,1,FALSE) -> JDA_PMM_ITM_EXPORT_ITEM_MASTER
A46: ITEM_EXPORT | B46: PMMDB | C46: apmmdb | D46: ITM_EXPORT | E46: JDA_PMM_ITM_EXPORT_ITEM_MASTER_FLAT | F46: 21/12/2025 19:39:54 | G46: 21/12/2025 19:41:05 | H46: =VLOOKUP(E46,UAC!A:A,1,FALSE) -> JDA_PMM_ITM_EXPORT_ITEM_MASTER_FLAT | I46: 6s
A47: ITEM_EXPORT | B47: PMMDB | C47: apmmdb | D47: ITM_EXPORT | E47: JDA_PMM_ITM_EXPORT_ITEM_MASTER_FLAT | F47: 22/12/2025 19:58:04 | G47: 22/12/2025 19:59:33 | H47: =VLOOKUP(E47,UAC!A:A,1,FALSE) -> JDA_PMM_ITM_EXPORT_ITEM_MASTER_FLAT
A48: ITEM_EXPORT | B48: PMMDB | C48: apmmdb | D48: ITM_EXPORT | E48: JDA_PMM_ITM_EXPORT_ITEM_PRICE | F48: 21/12/2025 19:30:31 | G48: 21/12/2025 19:30:59 | H48: =VLOOKUP(E48,UAC!A:A,1,FALSE) -> JDA_PMM_ITM_EXPORT_ITEM_PRICE | I48: 13s
A49: ITEM_EXPORT | B49: PMMDB | C49: apmmdb | D49: ITM_EXPORT | E49: JDA_PMM_ITM_EXPORT_ITEM_PRICE | F49: 22/12/2025 19:43:07 | G49: 22/12/2025 19:43:55 | H49: =VLOOKUP(E49,UAC!A:A,1,FALSE) -> JDA_PMM_ITM_EXPORT_ITEM_PRICE
A50: ITEM_EXPORT | B50: PMMDB | C50: apmmdb | D50: ITM_EXPORT | E50: JDA_PMM_ITM_EXPORT_ITEM_SET | F50: 21/12/2025 19:30:31 | G50: 21/12/2025 19:30:37 | H50: =VLOOKUP(E50,UAC!A:A,1,FALSE) -> JDA_PMM_ITM_EXPORT_ITEM_SET | I50: 31s
A51: ITEM_EXPORT | B51: PMMDB | C51: apmmdb | D51: ITM_EXPORT | E51: JDA_PMM_ITM_EXPORT_ITEM_SET | F51: 22/12/2025 19:43:07 | G51: 22/12/2025 19:43:14 | H51: =VLOOKUP(E51,UAC!A:A,1,FALSE) -> JDA_PMM_ITM_EXPORT_ITEM_SET
A52: ITEM_EXPORT | B52: PMMDB | C52: apmmdb | D52: ITM_EXPORT | E52: JDA_PMM_ITM_EXPORT_ITEM_STORE_PRICE | F52: 21/12/2025 19:30:31 | G52: 21/12/2025 19:39:54 | H52: =VLOOKUP(E52,UAC!A:A,1,FALSE) -> JDA_PMM_ITM_EXPORT_ITEM_STORE_PRICE | I52: 6s
A53: ITEM_EXPORT | B53: PMMDB | C53: apmmdb | D53: ITM_EXPORT | E53: JDA_PMM_ITM_EXPORT_ITEM_STORE_PRICE | F53: 22/12/2025 19:43:07 | G53: 22/12/2025 19:58:04 | H53: =VLOOKUP(E53,UAC!A:A,1,FALSE) -> JDA_PMM_ITM_EXPORT_ITEM_STORE_PRICE
A54: ITEM_EXPORT | B54: PMMDB | C54: apmmdb | D54: ITM_EXPORT | E54: JDA_PMM_TO_PROMO_ITM_MASTER_FLAT | F54: 21/12/2025 19:58:18 | G54: 21/12/2025 19:58:58 | H54: =VLOOKUP(E54,UAC!A:A,1,FALSE) -> JDA_PMM_TO_PROMO_ITM_MASTER_FLAT | I54: 7s
A55: ITEM_EXPORT | B55: PMMDB | C55: apmmdb | D55: ITM_EXPORT | E55: JDA_PMM_TO_PROMO_ITM_MASTER_FLAT | F55: 22/12/2025 20:15:24 | G55: 22/12/2025 20:16:00 | H55: =VLOOKUP(E55,UAC!A:A,1,FALSE) -> JDA_PMM_TO_PROMO_ITM_MASTER_FLAT
A56: ITEM_EXPORT | B56: PMMDB | C56: apmmdb | D56: ITM_EXPORT | E56: T_ITM_EXPORT | F56: 21/12/2025 19:58:59 | G56: 21/12/2025 19:59:04 | H56: =VLOOKUP(E56,UAC!A:A,1,FALSE) -> #N/A | I56: 13s
A57: ITEM_EXPORT | B57: PMMDB | C57: apmmdb | D57: ITM_EXPORT | E57: T_ITM_EXPORT | F57: 22/12/2025 20:16:01 | G57: 22/12/2025 20:16:06 | H57: =VLOOKUP(E57,UAC!A:A,1,FALSE) -> #N/A
A58: IMPORT_JDE_TABLES | B58: PMMDB | C58: apmmdb | D58: JDE_IMPORT_TABLES | E58: H_JDE_IMPORT_TABLES | F58: 21/12/2025 19:00:00 | G58: 21/12/2025 19:00:03 | H58: =VLOOKUP(E58,UAC!A:A,1,FALSE) -> #N/A | I58: 6s
A59: IMPORT_JDE_TABLES | B59: PMMDB | C59: apmmdb | D59: JDE_IMPORT_TABLES | E59: H_JDE_IMPORT_TABLES | F59: 22/12/2025 19:00:01 | G59: 22/12/2025 19:00:03 | H59: =VLOOKUP(E59,UAC!A:A,1,FALSE) -> #N/A
A60: IMPORT_JDE_TABLES | B60: PMMDB | C60: apmmdb | D60: JDE_IMPORT_TABLES | E60: JDA_PMM_JDE_IMPORT_AP_TERMS | F60: 21/12/2025 19:00:03 | G60: 21/12/2025 19:00:04 | H60: =VLOOKUP(E60,UAC!A:A,1,FALSE) -> JDA_PMM_JDE_IMPORT_AP_TERMS | I60: 7s
A61: IMPORT_JDE_TABLES | B61: PMMDB | C61: apmmdb | D61: JDE_IMPORT_TABLES | E61: JDA_PMM_JDE_IMPORT_AP_TERMS | F61: 22/12/2025 19:00:03 | G61: 22/12/2025 19:00:04 | H61: =VLOOKUP(E61,UAC!A:A,1,FALSE) -> JDA_PMM_JDE_IMPORT_AP_TERMS
A62: IMPORT_JDE_TABLES | B62: PMMDB | C62: apmmdb | D62: JDE_IMPORT_TABLES | E62: JDA_PMM_JDE_IMPORT_CKB_LOC | F62: 21/12/2025 19:00:50 | G62: 21/12/2025 19:00:52 | H62: =VLOOKUP(E62,UAC!A:A,1,FALSE) -> JDA_PMM_JDE_IMPORT_CKB_LOC | I62: 13s
A63: IMPORT_JDE_TABLES | B63: PMMDB | C63: apmmdb | D63: JDE_IMPORT_TABLES | E63: JDA_PMM_JDE_IMPORT_CKB_LOC | F63: 22/12/2025 19:16:45 | G63: 22/12/2025 19:16:50 | H63: =VLOOKUP(E63,UAC!A:A,1,FALSE) -> JDA_PMM_JDE_IMPORT_CKB_LOC
A64: IMPORT_JDE_TABLES | B64: PMMDB | C64: apmmdb | D64: JDE_IMPORT_TABLES | E64: JDA_PMM_JDE_IMPORT_STORE_MASTER | F64: 21/12/2025 19:00:14 | G64: 21/12/2025 19:00:49 | H64: =VLOOKUP(E64,UAC!A:A,1,FALSE) -> JDA_PMM_JDE_IMPORT_STORE_MASTER | I64: 6s
A65: IMPORT_JDE_TABLES | B65: PMMDB | C65: apmmdb | D65: JDE_IMPORT_TABLES | E65: JDA_PMM_JDE_IMPORT_STORE_MASTER | F65: 22/12/2025 19:00:13 | G65: 22/12/2025 19:16:43 | H65: =VLOOKUP(E65,UAC!A:A,1,FALSE) -> JDA_PMM_JDE_IMPORT_STORE_MASTER
A66: IMPORT_JDE_TABLES | B66: PMMDB | C66: apmmdb | D66: JDE_IMPORT_TABLES | E66: JDA_PMM_JDE_IMPORT_VENDOR_MASTER | F66: 21/12/2025 19:00:04 | G66: 21/12/2025 19:00:13 | H66: =VLOOKUP(E66,UAC!A:A,1,FALSE) -> JDA_PMM_JDE_IMPORT_VENDOR_MASTER | I66: 31s
A67: IMPORT_JDE_TABLES | B67: PMMDB | C67: apmmdb | D67: JDE_IMPORT_TABLES | E67: JDA_PMM_JDE_IMPORT_VENDOR_MASTER | F67: 22/12/2025 19:00:04 | G67: 22/12/2025 19:00:13 | H67: =VLOOKUP(E67,UAC!A:A,1,FALSE) -> JDA_PMM_JDE_IMPORT_VENDOR_MASTER
A68: IMPORT_JDE_TABLES | B68: PMMDB | C68: apmmdb | D68: JDE_IMPORT_TABLES | E68: T_JDE_IMPORT_TABLES | F68: 21/12/2025 19:00:52 | G68: 21/12/2025 19:00:57 | H68: =VLOOKUP(E68,UAC!A:A,1,FALSE) -> #N/A | I68: 1s
A69: IMPORT_JDE_TABLES | B69: PMMDB | C69: apmmdb | D69: JDE_IMPORT_TABLES | E69: T_JDE_IMPORT_TABLES | F69: 22/12/2025 19:16:51 | G69: 22/12/2025 19:16:56 | H69: =VLOOKUP(E69,UAC!A:A,1,FALSE) -> #N/A
A70: MCK_ITEM_CATALOG | B70: PMMDB | C70: apmmdb | D70: MCK_ITEM_CATALOG | E70: H_MCK_CAT | F70: 22/12/2025 08:00:01 | G70: 22/12/2025 08:00:02 | H70: =VLOOKUP(E70,UAC!A:A,1,FALSE) -> #N/A
A71: MCK_ITEM_CATALOG | B71: PMMDB | C71: apmmdb | D71: MCK_ITEM_CATALOG | E71: H_MCK_CAT | F71: 23/12/2025 08:00:01 | G71: 23/12/2025 08:00:02 | H71: =VLOOKUP(E71,UAC!A:A,1,FALSE) -> #N/A
A72: MCK_ITEM_CATALOG | B72: PMMDB | C72: apmmdb | D72: MCK_ITEM_CATALOG | E72: JDA_PMM_IMPORT_MCK_ITEM_CATALOG | F72: 22/12/2025 08:00:03 | G72: 22/12/2025 08:06:18 | H72: =VLOOKUP(E72,UAC!A:A,1,FALSE) -> JDA_PMM_IMPORT_MCK_ITEM_CATALOG
A73: MCK_ITEM_CATALOG | B73: PMMDB | C73: apmmdb | D73: MCK_ITEM_CATALOG | E73: JDA_PMM_IMPORT_MCK_ITEM_CATALOG | F73: 23/12/2025 08:00:02 | G73: 23/12/2025 08:06:27 | H73: =VLOOKUP(E73,UAC!A:A,1,FALSE) -> JDA_PMM_IMPORT_MCK_ITEM_CATALOG
A74: MCK_ITEM_CATALOG | B74: PMMDB | C74: apmmdb | D74: MCK_ITEM_CATALOG | E74: JDA_PMM_MCK_CATALOG_BB_ADJUSTMENT | F74: 22/12/2025 08:06:18 | G74: 22/12/2025 08:06:19 | H74: =VLOOKUP(E74,UAC!A:A,1,FALSE) -> JDA_PMM_MCK_CATALOG_BB_ADJUSTMENT
A75: MCK_ITEM_CATALOG | B75: PMMDB | C75: apmmdb | D75: MCK_ITEM_CATALOG | E75: JDA_PMM_MCK_CATALOG_BB_ADJUSTMENT | F75: 23/12/2025 08:06:27 | G75: 23/12/2025 08:06:28 | H75: =VLOOKUP(E75,UAC!A:A,1,FALSE) -> JDA_PMM_MCK_CATALOG_BB_ADJUSTMENT
A76: MCK_ITEM_CATALOG | B76: PMMDB | C76: apmmdb | D76: MCK_ITEM_CATALOG | E76: JDA_PMM_MCK_CATALOG_NEW_EXTRACT | F76: 22/12/2025 08:06:19 | G76: 22/12/2025 08:07:16 | H76: =VLOOKUP(E76,UAC!A:A,1,FALSE) -> JDA_PMM_MCK_CATALOG_NEW_EXTRACT
A77: MCK_ITEM_CATALOG | B77: PMMDB | C77: apmmdb | D77: MCK_ITEM_CATALOG | E77: JDA_PMM_MCK_CATALOG_NEW_EXTRACT | F77: 23/12/2025 08:06:28 | G77: 23/12/2025 08:07:26 | H77: =VLOOKUP(E77,UAC!A:A,1,FALSE) -> JDA_PMM_MCK_CATALOG_NEW_EXTRACT
A78: MCK_ITEM_CATALOG | B78: PMMDB | C78: apmmdb | D78: MCK_ITEM_CATALOG | E78: T_MCK_CAT | F78: 22/12/2025 08:07:16 | G78: 22/12/2025 08:07:17 | H78: =VLOOKUP(E78,UAC!A:A,1,FALSE) -> #N/A
A79: MCK_ITEM_CATALOG | B79: PMMDB | C79: apmmdb | D79: MCK_ITEM_CATALOG | E79: T_MCK_CAT | F79: 23/12/2025 08:07:26 | G79: 23/12/2025 08:07:27 | H79: =VLOOKUP(E79,UAC!A:A,1,FALSE) -> #N/A
A80: DAYEND_PROC | B80: PMMDB | C80: apmmdb | D80: MER_RPE_DAYEND | E80: H_MER_RPE_DAYEND | F80: 21/12/2025 19:25:30 | G80: 21/12/2025 19:25:32 | H80: =VLOOKUP(E80,UAC!A:A,1,FALSE) -> #N/A | I80: 1s
A81: DAYEND_PROC | B81: PMMDB | C81: apmmdb | D81: MER_RPE_DAYEND | E81: H_MER_RPE_DAYEND | F81: 22/12/2025 19:37:17 | G81: 22/12/2025 19:37:19 | H81: =VLOOKUP(E81,UAC!A:A,1,FALSE) -> #N/A
A82: DAYEND_PROC | B82: PMMDB | C82: apmmdb | D82: MER_RPE_DAYEND | E82: JDA_PMM_DYE_AUTOMKDN | F82: 21/12/2025 19:25:33 | G82: 21/12/2025 19:26:29 | H82: =VLOOKUP(E82,UAC!A:A,1,FALSE) -> JDA_PMM_DYE_AUTOMKDN | I82: 31s
A83: DAYEND_PROC | B83: PMMDB | C83: apmmdb | D83: MER_RPE_DAYEND | E83: JDA_PMM_DYE_AUTOMKDN | F83: 22/12/2025 19:37:20 | G83: 22/12/2025 19:38:01 | H83: =VLOOKUP(E83,UAC!A:A,1,FALSE) -> JDA_PMM_DYE_AUTOMKDN
A84: DAYEND_PROC | B84: PMMDB | C84: apmmdb | D84: MER_RPE_DAYEND | E84: JDA_PMM_DYE_FMTPDSMB | F84: 21/12/2025 19:27:05 | G84: 21/12/2025 19:29:01 | H84: =VLOOKUP(E84,UAC!A:A,1,FALSE) -> JDA_PMM_DYE_FMTPDSMB | I84: 6s
A85: DAYEND_PROC | B85: PMMDB | C85: apmmdb | D85: MER_RPE_DAYEND | E85: JDA_PMM_DYE_FMTPDSMB | F85: 22/12/2025 19:38:20 | G85: 22/12/2025 19:40:45 | H85: =VLOOKUP(E85,UAC!A:A,1,FALSE) -> JDA_PMM_DYE_FMTPDSMB
A86: DAYEND_PROC | B86: PMMDB | C86: apmmdb | D86: MER_RPE_DAYEND | E86: JDA_PMM_DYE_MAINTAIN_MCK_ITEM | F86: 21/12/2025 19:26:58 | G86: 21/12/2025 19:27:04 | H86: =VLOOKUP(E86,UAC!A:A,1,FALSE) -> JDA_PMM_DYE_MAINTAIN_MCK_ITEM | I86: 31s
A87: DAYEND_PROC | B87: PMMDB | C87: apmmdb | D87: MER_RPE_DAYEND | E87: JDA_PMM_DYE_MAINTAIN_MCK_ITEM | F87: 22/12/2025 19:38:14 | G87: 22/12/2025 19:38:20 | H87: =VLOOKUP(E87,UAC!A:A,1,FALSE) -> JDA_PMM_DYE_MAINTAIN_MCK_ITEM
A88: DAYEND_PROC | B88: PMMDB | C88: apmmdb | D88: MER_RPE_DAYEND | E88: JDA_PMM_DYE_PRCHDRSTS | F88: 21/12/2025 19:26:31 | G88: 21/12/2025 19:26:49 | H88: =VLOOKUP(E88,UAC!A:A,1,FALSE) -> JDA_PMM_DYE_PRCHDRSTS | I88: 6s
A89: DAYEND_PROC | B89: PMMDB | C89: apmmdb | D89: MER_RPE_DAYEND | E89: JDA_PMM_DYE_PRCHDRSTS | F89: 22/12/2025 19:38:02 | G89: 22/12/2025 19:38:09 | H89: =VLOOKUP(E89,UAC!A:A,1,FALSE) -> JDA_PMM_DYE_PRCHDRSTS
A90: DAYEND_PROC | B90: PMMDB | C90: apmmdb | D90: MER_RPE_DAYEND | E90: JDA_PMM_DYE_PRDDELBAT | F90: 21/12/2025 19:26:56 | G90: 21/12/2025 19:26:57 | H90: =VLOOKUP(E90,UAC!A:A,1,FALSE) -> JDA_PMM_DYE_PRDDELBAT | I90: 7s
A91: DAYEND_PROC | B91: PMMDB | C91: apmmdb | D91: MER_RPE_DAYEND | E91: JDA_PMM_DYE_PRDDELBAT | F91: 22/12/2025 19:38:13 | G91: 22/12/2025 19:38:14 | H91: =VLOOKUP(E91,UAC!A:A,1,FALSE) -> JDA_PMM_DYE_PRDDELBAT
A92: DAYEND_PROC | B92: PMMDB | C92: apmmdb | D92: MER_RPE_DAYEND | E92: JDA_PMM_DYE_PRDSTSUP | F92: 21/12/2025 19:26:52 | G92: 21/12/2025 19:26:53 | H92: =VLOOKUP(E92,UAC!A:A,1,FALSE) -> JDA_PMM_DYE_PRDSTSUP | I92: 6s
A93: DAYEND_PROC | B93: PMMDB | C93: apmmdb | D93: MER_RPE_DAYEND | E93: JDA_PMM_DYE_PRDSTSUP | F93: 22/12/2025 19:38:10 | G93: 22/12/2025 19:38:11 | H93: =VLOOKUP(E93,UAC!A:A,1,FALSE) -> JDA_PMM_DYE_PRDSTSUP
A94: DAYEND_PROC | B94: PMMDB | C94: apmmdb | D94: MER_RPE_DAYEND | E94: JDA_PMM_DYE_SLSBMPDAY | F94: 21/12/2025 19:26:49 | G94: 21/12/2025 19:26:51 | H94: =VLOOKUP(E94,UAC!A:A,1,FALSE) -> JDA_PMM_DYE_SLSBMPDAY | I94: 1s
A95: DAYEND_PROC | B95: PMMDB | C95: apmmdb | D95: MER_RPE_DAYEND | E95: JDA_PMM_DYE_SLSBMPDAY | F95: 22/12/2025 19:38:09 | G95: 22/12/2025 19:38:10 | H95: =VLOOKUP(E95,UAC!A:A,1,FALSE) -> JDA_PMM_DYE_SLSBMPDAY
A96: DAYEND_PROC | B96: PMMDB | C96: apmmdb | D96: MER_RPE_DAYEND | E96: JDA_PMM_DYE_STAT_SYNC | F96: 21/12/2025 19:29:02 | G96: 21/12/2025 19:29:10 | H96: =VLOOKUP(E96,UAC!A:A,1,FALSE) -> JDA_PMM_DYE_STAT_SYNC | I96: 13s
A97: DAYEND_PROC | B97: PMMDB | C97: apmmdb | D97: MER_RPE_DAYEND | E97: JDA_PMM_DYE_STAT_SYNC | F97: 22/12/2025 19:40:45 | G97: 22/12/2025 19:40:58 | H97: =VLOOKUP(E97,UAC!A:A,1,FALSE) -> JDA_PMM_DYE_STAT_SYNC
A98: DAYEND_PROC | B98: PMMDB | C98: apmmdb | D98: MER_RPE_DAYEND | E98: JDA_PMM_DYE_VPCSTSUP | F98: 21/12/2025 19:26:54 | G98: 21/12/2025 19:26:55 | H98: =VLOOKUP(E98,UAC!A:A,1,FALSE) -> JDA_PMM_DYE_VPCSTSUP | I98: 1s
A99: DAYEND_PROC | B99: PMMDB | C99: apmmdb | D99: MER_RPE_DAYEND | E99: JDA_PMM_DYE_VPCSTSUP | F99: 22/12/2025 19:38:12 | G99: 22/12/2025 19:38:13 | H99: =VLOOKUP(E99,UAC!A:A,1,FALSE) -> JDA_PMM_DYE_VPCSTSUP
A100: DAYEND_PROC | B100: PMMDB | C100: apmmdb | D100: MER_RPE_DAYEND | E100: T_MER_RPE_DAYEND | F100: 21/12/2025 19:29:10 | G100: 21/12/2025 19:29:15 | H100: =VLOOKUP(E100,UAC!A:A,1,FALSE) -> #N/A | I100: 1s
...

Sheet UAC
A1: Task | B1: Task Type | C1: Workflow | D1: Launch Time | E1: task-time | F1: Compare DU
A2: MASTER_PMMDB | B2: Workflow | D2: 46013.792 | E2: 46013.792 | F2: =_xlfn.IFNA(VLOOKUP(A2,APMMDB!E:E,1,FALSE),VLOOKUP(LEFT(A2, FIND("♦", SUBSTITUTE(A2, "_", "♦", LEN(A2)-LEN(SUBSTITUTE(A2,"_","")))) - 1),APMMDB!D:D,1,FALSE)) -> #N/A
A3: JDA_PMM_COST_ELE_RETAIL_COMP_RPT | B3: Linux/Unix | C3: BUILD_COMP_REP_PMMDB | D3: 46013.792 | E3: 46013.792 | F3: =_xlfn.IFNA(VLOOKUP(A3,APMMDB!E:E,1,FALSE),VLOOKUP(LEFT(A3, FIND("♦", SUBSTITUTE(A3, "_", "♦", LEN(A3)-LEN(SUBSTITUTE(A3,"_","")))) - 1),APMMDB!D:D,1,FALSE)) -> #N/A
A4: JDA_PMM_DFU_DFUVIEW_PPARM_COMP | B4: Linux/Unix | C4: BUILD_COMP_REP_PMMDB | D4: 46013.792 | E4: 46013.792 | F4: =_xlfn.IFNA(VLOOKUP(A4,APMMDB!E:E,1,FALSE),VLOOKUP(LEFT(A4, FIND("♦", SUBSTITUTE(A4, "_", "♦", LEN(A4)-LEN(SUBSTITUTE(A4,"_","")))) - 1),APMMDB!D:D,1,FALSE)) -> #N/A
A5: JDA_PMM_CSP_EXPORT_CASEPACK | B5: Linux/Unix | C5: CSP_EXPORT_PMMDB | D5: 46013.792 | E5: 46013.792 | F5: =_xlfn.IFNA(VLOOKUP(A5,APMMDB!E:E,1,FALSE),VLOOKUP(LEFT(A5, FIND("♦", SUBSTITUTE(A5, "_", "♦", LEN(A5)-LEN(SUBSTITUTE(A5,"_","")))) - 1),APMMDB!D:D,1,FALSE)) -> JDA_PMM_CSP_EXPORT_CASEPACK
A6: JDA_PMM_CSP_EXPORT_CASEPACK_AF | B6: Linux/Unix | C6: CSP_EXPORT_PMMDB | D6: 46013.792 | E6: 46013.792 | F6: =_xlfn.IFNA(VLOOKUP(A6,APMMDB!E:E,1,FALSE),VLOOKUP(LEFT(A6, FIND("♦", SUBSTITUTE(A6, "_", "♦", LEN(A6)-LEN(SUBSTITUTE(A6,"_","")))) - 1),APMMDB!D:D,1,FALSE)) -> JDA_PMM_CSP_EXPORT_CASEPACK_AF
A7: JDA_PMM_CSP_EXPORT_CASEPACK_COST | B7: Linux/Unix | C7: CSP_EXPORT_PMMDB | D7: 46013.792 | E7: 46013.792 | F7: =_xlfn.IFNA(VLOOKUP(A7,APMMDB!E:E,1,FALSE),VLOOKUP(LEFT(A7, FIND("♦", SUBSTITUTE(A7, "_", "♦", LEN(A7)-LEN(SUBSTITUTE(A7,"_","")))) - 1),APMMDB!D:D,1,FALSE)) -> JDA_PMM_CSP_EXPORT_CASEPACK_COST
A8: JDA_PMM_CSP_EXPORT_CASEPACK_FLAT | B8: Linux/Unix | C8: CSP_EXPORT_PMMDB | D8: 46013.792 | E8: 46013.792 | F8: =_xlfn.IFNA(VLOOKUP(A8,APMMDB!E:E,1,FALSE),VLOOKUP(LEFT(A8, FIND("♦", SUBSTITUTE(A8, "_", "♦", LEN(A8)-LEN(SUBSTITUTE(A8,"_","")))) - 1),APMMDB!D:D,1,FALSE)) -> JDA_PMM_CSP_EXPORT_CASEPACK_FLAT
A9: JDA_PMM_CSP_REJECT_REP | B9: Linux/Unix | C9: CSP_EXPORT_PMMDB | D9: 46013.792 | E9: 46013.792 | F9: =_xlfn.IFNA(VLOOKUP(A9,APMMDB!E:E,1,FALSE),VLOOKUP(LEFT(A9, FIND("♦", SUBSTITUTE(A9, "_", "♦", LEN(A9)-LEN(SUBSTITUTE(A9,"_","")))) - 1),APMMDB!D:D,1,FALSE)) -> JDA_PMM_CSP_REJECT_REP
A10: JDA_PMM_EXPORT_CHG_ALLOW | B10: Linux/Unix | C10: CSP_EXPORT_PMMDB | D10: 46013.792 | E10: 46013.792 | F10: =_xlfn.IFNA(VLOOKUP(A10,APMMDB!E:E,1,FALSE),VLOOKUP(LEFT(A10, FIND("♦", SUBSTITUTE(A10, "_", "♦", LEN(A10)-LEN(SUBSTITUTE(A10,"_","")))) - 1),APMMDB!D:D,1,FALSE)) -> JDA_PMM_EXPORT_CHG_ALLOW
A11: JDA_PMM_IMPORT_PO_ALLOCATION | B11: Linux/Unix | C11: IMP_PRM_PMM_PMMDB | D11: 46013.792 | E11: 46013.792 | F11: =_xlfn.IFNA(VLOOKUP(A11,APMMDB!E:E,1,FALSE),VLOOKUP(LEFT(A11, FIND("♦", SUBSTITUTE(A11, "_", "♦", LEN(A11)-LEN(SUBSTITUTE(A11,"_","")))) - 1),APMMDB!D:D,1,FALSE)) -> JDA_PMM_IMPORT_PO_ALLOCATION
A12: JDA_PMM_IMPORT_PROMO | B12: Linux/Unix | C12: IMP_PRM_PMM_PMMDB | D12: 46013.792 | E12: 46013.792 | F12: =_xlfn.IFNA(VLOOKUP(A12,APMMDB!E:E,1,FALSE),VLOOKUP(LEFT(A12, FIND("♦", SUBSTITUTE(A12, "_", "♦", LEN(A12)-LEN(SUBSTITUTE(A12,"_","")))) - 1),APMMDB!D:D,1,FALSE)) -> JDA_PMM_IMPORT_PROMO
A13: JDA_PMM_IMPORT_PLANOGRAM | B13: Linux/Unix | C13: IMPORT_PROCS_PMMDB | D13: 46013.792 | E13: 46013.792 | F13: =_xlfn.IFNA(VLOOKUP(A13,APMMDB!E:E,1,FALSE),VLOOKUP(LEFT(A13, FIND("♦", SUBSTITUTE(A13, "_", "♦", LEN(A13)-LEN(SUBSTITUTE(A13,"_","")))) - 1),APMMDB!D:D,1,FALSE)) -> JDA_PMM_IMPORT_PLANOGRAM
A14: JDA_PMM_INT_NOTIFICATIONS | B14: Linux/Unix | C14: IMPORT_PROCS_PMMDB | D14: 46013.792 | E14: 46013.792 | F14: =_xlfn.IFNA(VLOOKUP(A14,APMMDB!E:E,1,FALSE),VLOOKUP(LEFT(A14, FIND("♦", SUBSTITUTE(A14, "_", "♦", LEN(A14)-LEN(SUBSTITUTE(A14,"_","")))) - 1),APMMDB!D:D,1,FALSE)) -> JDA_PMM_INT_NOTIFICATIONS
... A211: JDA_PMM_WIS_IMPORT_SDIPHYDTI | B211: Linux/Unix | C211: WIS_IMPORT_PMMDB | D211: 46013.792 | E211: 46013.792 | F211: =_xlfn.IFNA(VLOOKUP(A211,APMMDB!E:E,1,FALSE),VLOOKUP(LEFT(A211, FIND("♦", SUBSTITUTE(A211, "_", "♦", LEN(A211)-LEN(SUBSTITUTE(A211,"_","")))) - 1),APMMDB!D:D,1,FALSE)) -> JDA_PMM_WIS_IMPORT_SDIPHYDTI
